nu_gpa/__init__.py
nu_gpa-1.0.4.dist-info/LICENSE.txt
nu_gpa-1.0.4.dist-info/METADATA
nu_gpa-1.0.4.dist-info/RECORD
nu_gpa-1.0.4.dist-info/WHEEL
nu_gpa-1.0.4.dist-info/entry_points.txt
nu_gpa-1.0.4.dist-info/top_level.txt
