Metadata-Version: 2.1
Name: nu-gpa
Version: 1.0.4
Summary: A command line package to calculate GPA of semester results specially for professional courses like CSE, ECE, BBA etc. offered by National University, Bangladesh.
Home-page: https://github.com/shahed-shd/nu_gpa
Author: Md. Shahedul Islam Shahed
Author-email: shahed.shd777@gmail.com
License: UNKNOWN
Keywords: gpa semester result nu nubd cse ece bba course education
Platform: UNKNOWN
Classifier: Development Status :: 5 - Production/Stable
Classifier: Intended Audience :: Education
Classifier: Topic :: Education
Classifier: License :: OSI Approved :: MIT License
Classifier: Programming Language :: Python :: 2
Classifier: Programming Language :: Python :: 2.7
Classifier: Programming Language :: Python :: 3
Classifier: Programming Language :: Python :: 3.4
Classifier: Programming Language :: Python :: 3.5
Classifier: Programming Language :: Python :: 3.6
